CHANGES.txt
LICENSE.txt
MANIFEST.in
README.txt
setup.py
docs/client.txt
docs/provider.txt
pyoauth2_shift/__init__.py
pyoauth2_shift/client.py
pyoauth2_shift/provider.py
pyoauth2_shift/utils.py
pyoauth2_shift.egg-info/PKG-INFO
pyoauth2_shift.egg-info/SOURCES.txt
pyoauth2_shift.egg-info/dependency_links.txt
pyoauth2_shift.egg-info/requires.txt
pyoauth2_shift.egg-info/top_level.txt
pyoauth2_shift/tests/__init__.py
pyoauth2_shift/tests/test_client.py
pyoauth2_shift/tests/test_integration.py
pyoauth2_shift/tests/test_provider.py
pyoauth2_shift/tests/test_utils.py