Metadata-Version: 1.0
Name: pyoauth2-shift
Version: 0.0.1
Summary: OAuth 2.0 compliant client and server library.
Home-page: https://github.com/Songbee/pyoauth2
Author: GraphEffect, Inc.
Author-email: nate@grapheffect.com
License: LICENSE.txt
Platform: UNKNOWN
